README.md
setup.cfg
setup.py
sortme/__init__.py
sortme/errors.py
sortme/group.py
sortme/main.py
sortme/groups/__init__.py
sortme/groups/problems.py
sortme/groups/users.py
sortme_api.egg-info/PKG-INFO
sortme_api.egg-info/SOURCES.txt
sortme_api.egg-info/dependency_links.txt
sortme_api.egg-info/requires.txt
sortme_api.egg-info/top_level.txt